{
  "Інформатика": ["amber/800", "black"],
  "Історія": ["brown/500", "white"],
  "Алгебра": ["red/600", "white"],
  "Англійська мова": ["yellow/600", "black"],
  "Біологія": ["lime/500", "black"],
  "Географія": ["lightBlue/400", "black"],
  "Геометрія": ["red/600", "white"],
  "Математика": ["red/600", "white"],
  "Природознавство": ["purple/600", "white"],
  "Українська література": ["green/400", "black"],
  "Українська мова": ["green/400", "black"],
  "Українська": ["green/400", "black"],
  "Фізика (практика)": ["deepPurple/500", "white"],
  "Фізика": ["deepPurple/500", "white"],
  "Фізкультура": ["amber/800", "black"],
  "Хімія": ["purple/600", "white"]
}
